pyschemata/__init__.py
pyschemata/schemastore/__init__.py
pyschemata/schemastore/catalog.json
pyschemata/schemastore/index.json
pyschemata/schemastore/vendor_lock.json
pyschemata/schemastore/jsondata/001a7e818ac0.json
pyschemata/schemastore/jsondata/002873801e56.json
pyschemata/schemastore/jsondata/0056a3bcb8de.json
pyschemata/schemastore/jsondata/0103aa4ef81f.json
pyschemata/schemastore/jsondata/015945c8c269.json
pyschemata/schemastore/jsondata/01f0adf24c2d.json
pyschemata/schemastore/jsondata/0233d86b30c8.json
pyschemata/schemastore/jsondata/029ecf254898.json
pyschemata/schemastore/jsondata/0301d17f3a24.json
pyschemata/schemastore/jsondata/038e26acbd4c.json
pyschemata/schemastore/jsondata/04abba0ec479.json
pyschemata/schemastore/jsondata/05ba36a53a80.json
pyschemata/schemastore/jsondata/05e9591ab0e4.json
pyschemata/schemastore/jsondata/061799995164.json
pyschemata/schemastore/jsondata/06355e69f0a4.json
pyschemata/schemastore/jsondata/067d604ce179.json
pyschemata/schemastore/jsondata/06ddc8c44f1b.json
pyschemata/schemastore/jsondata/071392acc11d.json
pyschemata/schemastore/jsondata/075d5cd70b10.json
pyschemata/schemastore/jsondata/07cc9065a2db.json
pyschemata/schemastore/jsondata/0903cccaadbe.json
pyschemata/schemastore/jsondata/0914855a1f0c.json
pyschemata/schemastore/jsondata/0b0b85539647.json
pyschemata/schemastore/jsondata/0c9183a0bc16.json
pyschemata/schemastore/jsondata/0ce7ce7e759f.json
pyschemata/schemastore/jsondata/0cecd8c71af9.json
pyschemata/schemastore/jsondata/0d005b093579.json
pyschemata/schemastore/jsondata/0d4c9e3f76ee.json
pyschemata/schemastore/jsondata/0d5725c0be98.json
pyschemata/schemastore/jsondata/0d8ec2f3e1cf.json
pyschemata/schemastore/jsondata/0daaf82fd32d.json
pyschemata/schemastore/jsondata/0dcee47bb21a.json
pyschemata/schemastore/jsondata/0dfd142959f2.json
pyschemata/schemastore/jsondata/0fda0903a714.json
pyschemata/schemastore/jsondata/10d0aa37cfe2.json
pyschemata/schemastore/jsondata/110a75e145a3.json
pyschemata-22.10.24b1.dist-info/METADATA
pyschemata-22.10.24b1.dist-info/WHEEL
pyschemata-22.10.24b1.dist-info/RECORD
