Metadata-Version: 2.1
Name: pyschemata
Version: 22.10.24b1
Summary: Bringing SchemaStore to python as a data package
Project-URL: Source code, https://github.com/sirosen/pyschemata
Author-email: Stephen Rosen <sirosen0@gmail.com>
Classifier: Development Status :: 4 - Beta
Classifier: Intended Audience :: Developers
Classifier: License :: OSI Approved :: Apache Software License
Classifier: Programming Language :: Python :: 3
Requires-Python: >=3.7
Requires-Dist: importlib-resources; python_version < '3.9'
